arknights_farmer/__init__.py
arknights_farmer/__main__.py
arknights_farmer/farmer.py
arknights_farmer/stage.py
arknights_farmer/assets/auto_off.png
arknights_farmer/assets/combat.png
arknights_farmer/assets/exit_battle.png
arknights_farmer/assets/home.png
arknights_farmer/assets/lvlup.png
arknights_farmer/assets/mission_start.png
arknights_farmer/assets/sanity_out.png
arknights_farmer/assets/trust_meter.png
arknights_farmer/assets/chapter/1.png
arknights_farmer/assets/chapter/2.png
arknights_farmer/assets/chapter/3.png
arknights_farmer/assets/chapter/4.png
arknights_farmer/assets/chapter/5.png
arknights_farmer/assets/chapter/6.png
arknights_farmer/assets/daily_resources/a.png
arknights_farmer/assets/daily_resources/ap.png
arknights_farmer/assets/daily_resources/b.png
arknights_farmer/assets/daily_resources/c.png
arknights_farmer/assets/daily_resources/ca.png
arknights_farmer/assets/daily_resources/ce.png
arknights_farmer/assets/daily_resources/d.png
arknights_farmer/assets/daily_resources/ls.png
arknights_farmer/assets/daily_resources/sk.png
arknights_farmer/assets/stages/1/1-1.png
arknights_farmer/assets/stages/1/1-10.png
arknights_farmer/assets/stages/1/1-12.png
arknights_farmer/assets/stages/1/1-3.png
arknights_farmer/assets/stages/1/1-4.png
arknights_farmer/assets/stages/1/1-5.png
arknights_farmer/assets/stages/1/1-6.png
arknights_farmer/assets/stages/1/1-7.png
arknights_farmer/assets/stages/1/1-8.png
arknights_farmer/assets/stages/1/1-9.png
arknights_farmer/assets/stages/2/2-1.png
arknights_farmer/assets/stages/2/2-10.png
arknights_farmer/assets/stages/2/2-2.png
arknights_farmer/assets/stages/2/2-3.png
arknights_farmer/assets/stages/2/2-4.png
arknights_farmer/assets/stages/2/2-5.png
arknights_farmer/assets/stages/2/2-6.png
arknights_farmer/assets/stages/2/2-7.png
arknights_farmer/assets/stages/2/2-8.png
arknights_farmer/assets/stages/2/2-9.png
arknights_farmer/assets/stages/2/s/s2-1.png
arknights_farmer/assets/stages/2/s/s2-10.png
arknights_farmer-2020.12.18.dist-info/LICENSE
arknights_farmer-2020.12.18.dist-info/METADATA
arknights_farmer-2020.12.18.dist-info/WHEEL
arknights_farmer-2020.12.18.dist-info/entry_points.txt
arknights_farmer-2020.12.18.dist-info/top_level.txt
arknights_farmer-2020.12.18.dist-info/RECORD
