Metadata-Version: 2.1
Name: arknights-farmer
Version: 2020.12.18
Summary: Farming assistant for Arknights
Home-page: https://github.com/cytopz/arknights-farmer
Author: cytopz
Author-email: cytopz@protonmail.com
License: MIT
Platform: UNKNOWN
Classifier: Development Status :: 3 - Alpha
Classifier: Programming Language :: Python :: 3 :: Only
Classifier: Operating System :: OS Independent
Classifier: Topic :: Games/Entertainment
Classifier: License :: OSI Approved :: MIT License
Requires-Python: >=3.7.4
Requires-Dist: gacha-elper
Requires-Dist: urllib3
Requires-Dist: requests
